files3/__init__.py
files3/_cmd_entry.py
files3/f3bool.py
files3/f3core.py
files3/f3info.py
files3/f3io.py
files3/f3shell.py
files3/f3test.py
files3/f3utils.py
files3-0.9.3.dist-info/METADATA
files3-0.9.3.dist-info/WHEEL
files3-0.9.3.dist-info/entry_points.txt
files3-0.9.3.dist-info/top_level.txt
files3-0.9.3.dist-info/RECORD
